Metadata-Version: 1.1
Name: percol
Version: 0.1.0
Summary: Adds flavor of interactive filtering to the traditional pipe concept of shell
Home-page: https://github.com/mooz/percol
Author: mooz
Author-email: stillpedant@gmail.com
License: MIT
Keywords: anything.el unite.vim dmenu shell pipe filter curses
Platform: UNKNOWN
Classifier: Environment :: Console :: Curses
Classifier: License :: OSI Approved :: MIT License
Classifier: Operating System :: POSIX
Classifier: Programming Language :: Python
Classifier: Topic :: Text Processing :: Filters
Classifier: Topic :: Text Editors :: Emacs
Classifier: Topic :: Utilities
